<?xml version="1.0" encoding="utf-8" ?>
<Defs>
    <ThingDef ParentName="ApparelMakeableBase" Name="MFS_LightArmorBase" Abstract="true">
        <recipeMaker>
            <researchPrerequisite>MFS_SouthernProtectiveArmor</researchPrerequisite>
            <unfinishedThingDef>UnfinishedApparel</unfinishedThingDef>
            <recipeUsers>
                <li>DankPyon_TailorsBench</li>
                <!-- add vanilla workbenches -->
            </recipeUsers>
        </recipeMaker>
        <tradeability>Sellable</tradeability>        
        <techLevel>Medieval</techLevel>        
        <thingCategories>
            <li>ApparelArmor</li>
        </thingCategories>
        <apparel>
            <defaultOutfitTags>
                <li>Worker</li>
                <li>Soldier</li>
            </defaultOutfitTags>
            <canBeDesiredForIdeo>true</canBeDesiredForIdeo>
            <countsAsClothingForNudity>false</countsAsClothingForNudity>
            <developmentalStageFilter>Child, Adult</developmentalStageFilter>           
        </apparel>
    </ThingDef>

    <!-- Cloth Sash -->

    <ThingDef ParentName="MFS_LightArmorBase">
        <defName>MFS_ClothSash</defName>
        <label>cloth sash</label>
        <description>A double sash made from thick cloth that is worn across the body.\nA double layer sash made from thicker layers of clothing in order to protect the body not just from the sun but from blows of an enemy as well. Practical for those who wander the desert.</description>
        <graphicData>
            <texPath>Apparel/Armor/LightArmor/Cloth_Sash/Cloth_Sash</texPath>
            <graphicClass>Graphic_Single</graphicClass>
        </graphicData>
        <recipeMaker>
            <researchPrerequisite>MFS_SouthernProtectiveArmor</researchPrerequisite>            
            <skillRequirements>
                <Crafting>4</Crafting>
            </skillRequirements>
        </recipeMaker>
        <costStuffCount>100</costStuffCount> <!-- 75 ? -->
        <stuffCategories>
            <li>Fabric</li>
        </stuffCategories>
        <statBases>
            <MaxHitPoints>150</MaxHitPoints> <!-- 100 -->
            <WorkToMake>7400</WorkToMake>
            <Mass>2</Mass>
            <StuffEffectMultiplierArmor>0.3</StuffEffectMultiplierArmor>
            <StuffEffectMultiplierInsulation_Cold>0.6</StuffEffectMultiplierInsulation_Cold>
            <StuffEffectMultiplierInsulation_Heat>0.5</StuffEffectMultiplierInsulation_Heat>
            <EquipDelay>6</EquipDelay>
        </statBases>
        <apparel>
            <bodyPartGroups>
                <li>Neck</li>
                <li>Torso</li>
                <li>Arms</li>
                <li>Shoulders</li>
                <li>Legs</li>
            </bodyPartGroups>
            <wornGraphicPath>Apparel/Armor/LightArmor/Cloth_Sash/Cloth_Sash</wornGraphicPath>
            <tags>
                <li>MFS_LightArmor</li>
            </tags>
            <layers>
                <li>Middle</li>
                <li>Shell</li>
            </layers>
        </apparel>
        <colorGenerator Class="ColorGenerator_StandardApparel"/>
    </ThingDef>

    <!-- Leather Robe  -->

    <ThingDef ParentName="MFS_LightArmorBase">
        <defName>MFS_LeatherRobe</defName>
        <label>cloth sash</label>
        <description>This patchwork of leather robe requires not a lot of time or skill to put together, but provides some amount of protection. A thin layer of fabric is sometimes sewn inside it so the stitching and the leather do not rub against the skin.</description>
        <graphicData>
            <texPath>Apparel/Armor/LightArmor/Leather_Robe/Leather_Robe</texPath>
            <graphicClass>Graphic_Single</graphicClass>
        </graphicData>
        <recipeMaker>
            <researchPrerequisite>MFS_SouthernProtectiveArmor</researchPrerequisite>            
            <skillRequirements>
                <Crafting>3</Crafting>
            </skillRequirements>
        </recipeMaker>
        <costStuffCount>75</costStuffCount> 
        <stuffCategories>
            <li>Leathery</li>
        </stuffCategories>
        <statBases>
            <MaxHitPoints>120</MaxHitPoints> <!-- 100-120 -->
            <WorkToMake>10000</WorkToMake>
            <Mass>2.5</Mass>
            <StuffEffectMultiplierArmor>0.47</StuffEffectMultiplierArmor>
            <StuffEffectMultiplierInsulation_Cold>0.3</StuffEffectMultiplierInsulation_Cold>
            <StuffEffectMultiplierInsulation_Heat>0.2</StuffEffectMultiplierInsulation_Heat>
            <EquipDelay>6</EquipDelay>
        </statBases>
        <apparel>
            <bodyPartGroups>
                <li>Neck</li>
                <li>Torso</li>
                <li>Arms</li>
                <li>Shoulders</li>
                <li>Legs</li>
            </bodyPartGroups>
            <wornGraphicPath>Apparel/Armor/LightArmor/Leather_Robe/Leather_Robe</wornGraphicPath>
            <tags>
                <li>MFS_LightArmor</li>
            </tags>
            <layers>
                <li>Middle</li>
            </layers>
        </apparel>
        <colorGenerator Class="ColorGenerator_StandardApparel"/>
    </ThingDef>

    <!-- Light Gladiator Armor  -->

   <ThingDef ParentName="MFS_LightArmorBase">
        <defName>MFS_LightGladiatorArmor</defName>
        <label>light gladiator armor</label>
        <description>Warriors of the southern arenas often fight in lighter armor for its agility, to show off their well-muscled bodies to intimidate enemies and to entertain the masses with bloodshed. Thus this armor is made of straps and thick fabric padding for local protection.</description>
        <graphicData>
            <texPath>Apparel/Armor/LightArmor/Light_Gladiator_Armor/Light_Gladiator_Armor</texPath>
            <graphicClass>Graphic_Single</graphicClass>
            <shaderType>CutoutComplex</shaderType>        
        </graphicData>
        <recipeMaker>
            <skillRequirements>
            <researchPrerequisite>MFS_SouthernProtectiveArmor</researchPrerequisite>
                <Crafting>5</Crafting>
            </skillRequirements>
        </recipeMaker>
        <costStuffCount>50</costStuffCount> 
        <stuffCategories>
            <li>Fabric</li>
        </stuffCategories>
        <costList>
            <Leather_Heavy>10</Leather_Heavy>
        </costList>
        <statBases>
            <MaxHitPoints>125</MaxHitPoints> 
            <WorkToMake>10800</WorkToMake>
            <Mass>3</Mass>
            <StuffEffectMultiplierArmor>0.5</StuffEffectMultiplierArmor>
<!--             <StuffEffectMultiplierInsulation_Cold>0.3</StuffEffectMultiplierInsulation_Cold>
            <StuffEffectMultiplierInsulation_Heat>0.2</StuffEffectMultiplierInsulation_Heat> no insulation on the miro -->
            <EquipDelay>1.5</EquipDelay> 
        </statBases>
        <equippedStatOffsets>
            <MoveSpeed>0.5</MoveSpeed>
            <MeleeDodgeChance>0.5</MeleeDodgeChance>
        </equippedStatOffsets>
        <apparel>
            <bodyPartGroups>
                <li>Neck</li>
                <li>Torso</li>
                <li>Arms</li>
                <li>Shoulders</li>
                <li>Legs</li>
            </bodyPartGroups>
            <wornGraphicPath>Apparel/Armor/LightArmor/Light_Gladiator_Armor/Light_Gladiator_Armor</wornGraphicPath>
            <tags>
                <li>MFS_LightArmor</li>
            </tags>
            <layers>
                <li>Middle</li>
                <li>Shell</li>
            </layers>
        </apparel>
        <!-- <colorGenerator Class="ColorGenerator_StandardApparel"/> -->
    </ThingDef>

   <!-- Linothorax  -->

   <ThingDef ParentName="MFS_LightArmorBase">
        <defName>MFS_Linothorax</defName>
        <label>linothorax</label>
        <description>Despite being made out of fabric, linothorax provide a high degree of protection. Its light nature means it can be worn over most clothing, and it does not weigh down the wearer. However, it only covers the vital organs of the body.</description>
        <graphicData>
            <texPath>Apparel/Armor/LightArmor/Linothorax/Linothorax</texPath>
            <graphicClass>Graphic_Single</graphicClass>
        </graphicData>
        <recipeMaker>
            <researchPrerequisite>MFS_SouthernProtectiveArmor</researchPrerequisite>            
            <skillRequirements>
                <Crafting>4</Crafting>
            </skillRequirements>
        </recipeMaker>
        <costList>
            <DankPyon_Linen>70</DankPyon_Linen>
        </costList> 
        <statBases>
            <MaxHitPoints>200</MaxHitPoints> 
            <WorkToMake>15000</WorkToMake>
            <Mass>5</Mass>
            <ArmorRating_Sharp>0.31</ArmorRating_Sharp> <!-- about 50% metallic flat armor value -->
            <ArmorRating_Blunt>0.14</ArmorRating_Blunt>
            <Insulation_Heat>3</Insulation_Heat>
            <EquipDelay>12</EquipDelay> <!-- MO Lamellar = 10 -->
        </statBases>
        <apparel>
            <bodyPartGroups>
                <li>Torso</li>
                <li>Shoulders</li>
            </bodyPartGroups>
            <wornGraphicPath>Apparel/Armor/LightArmor/Linothorax/Linothorax</wornGraphicPath>
            <tags>
                <li>MFS_LightArmor</li>
            </tags>
            <layers>
                <li>Shell</li>
            </layers>
        </apparel>
        <colorGenerator Class="ColorGenerator_StandardApparel"/>
    </ThingDef>

    <!-- Padded Vest -->

   <ThingDef ParentName="MFS_LightArmorBase">
        <defName>MFS_PaddedVest</defName>
        <label>padded vest</label>
        <description>A thickly vest to wear over clothing. A widespread solution for self-defense in the south. The pockets of air between the padding provide some amount of insulation.</description>
        <graphicData>
            <texPath>Apparel/Armor/LightArmor/Padded_Vest/Padded_Vest</texPath>
            <graphicClass>Graphic_Single</graphicClass>
        </graphicData>
        <recipeMaker>
            <researchPrerequisite>MFS_SouthernProtectiveArmor</researchPrerequisite>            
            <skillRequirements>
                <Crafting>4</Crafting>
            </skillRequirements>
        </recipeMaker>
        <costStuffCount>70</costStuffCount> 
        <stuffCategories>
            <li>Fabric</li>
        </stuffCategories>
        <statBases>
            <MaxHitPoints>150</MaxHitPoints> <!-- 100-120 -->
            <WorkToMake>10000</WorkToMake>
            <Mass>3</Mass>
            <StuffEffectMultiplierArmor>0.3</StuffEffectMultiplierArmor>
            <StuffEffectMultiplierInsulation_Cold>0.2</StuffEffectMultiplierInsulation_Cold>
            <StuffEffectMultiplierInsulation_Heat>0.3</StuffEffectMultiplierInsulation_Heat>
            <EquipDelay>5</EquipDelay>
        </statBases>
        <apparel>
            <bodyPartGroups>
                <li>Torso</li>
                <li>Arms</li>
                <li>Shoulders</li>
                <li>Legs</li>
            </bodyPartGroups>
            <wornGraphicPath>Apparel/Armor/LightArmor/Padded_Vest/Padded_Vest</wornGraphicPath>
            <tags>
                <li>MFS_LightArmor</li>
            </tags>
            <layers>
                <li>Middle</li>
            </layers>
        </apparel>
        <colorGenerator Class="ColorGenerator_StandardApparel"/>
    </ThingDef>

    <!-- Stitched Armor -->

   <ThingDef ParentName="MFS_LightArmorBase">
        <defName>MFS_StitchedArmor</defName>
        <label>stiched armor</label>
        <description>Made of leather strips sewn together, this armor allows the wearer to wear some lighter armor underneath.</description>
        <graphicData>
            <texPath>Apparel/Armor/LightArmor/Stitched_Armor/Stitched_Armor</texPath>
            <graphicClass>Graphic_Single</graphicClass>
            <shaderType>CutoutComplex</shaderType>            
        </graphicData>
        <recipeMaker>
            <researchPrerequisite>MFS_SouthernProtectiveArmor</researchPrerequisite>            
            <skillRequirements>
                <Crafting>6</Crafting>
            </skillRequirements>
        </recipeMaker>
        <costStuffCount>85</costStuffCount> 
        <stuffCategories>
            <li>Leathery</li>
        </stuffCategories>
        <statBases>
            <MaxHitPoints>250</MaxHitPoints> 
            <WorkToMake>17400</WorkToMake>
            <Mass>9</Mass>
            <StuffEffectMultiplierArmor>0.62</StuffEffectMultiplierArmor>
            <StuffEffectMultiplierInsulation_Cold>0.8</StuffEffectMultiplierInsulation_Cold>
            <StuffEffectMultiplierInsulation_Heat>0.35</StuffEffectMultiplierInsulation_Heat>
            <EquipDelay>16</EquipDelay> <!-- MO Plate = 15 -->
        </statBases>
        <equippedStatOffsets>
            <MoveSpeed>-0.2</MoveSpeed>
        </equippedStatOffsets>
        <apparel>
            <bodyPartGroups>
                <li>Torso</li>
                <li>Neck</li>
                <li>Arms</li>
                <li>Shoulders</li>
                <li>Legs</li>
            </bodyPartGroups>
            <wornGraphicPath>Apparel/Armor/LightArmor/Stitched_Armor/Stitched_Armor</wornGraphicPath>
            <tags>
                <li>MFS_LightArmor</li>
            </tags>
            <layers>
                <li>Middle</li>
            </layers>
        </apparel>
        <colorGenerator Class="ColorGenerator_StandardApparel"/>
    </ThingDef>



</Defs>
